shtym/__init__.py
shtym/_version.py
shtym/application.py
shtym/cli.py
shtym/exceptions.py
shtym/py.typed
shtym/domain/__init__.py
shtym/domain/processor.py
shtym/domain/profile.py
shtym/infrastructure/__init__.py
shtym/infrastructure/fileio.py
shtym/infrastructure/llm_profile.py
shtym/infrastructure/profile_parsers.py
shtym/infrastructure/profile_repository.py
shtym/infrastructure/stdio.py
shtym/infrastructure/llm_clients/__init__.py
shtym/infrastructure/llm_clients/factory.py
shtym/infrastructure/llm_clients/ollama_client.py
shtym/infrastructure/processors/__init__.py
shtym/infrastructure/processors/factory.py
shtym/infrastructure/processors/llm_processor.py
shtym-0.2.0.dist-info/licenses/LICENSE
shtym-0.2.0.dist-info/METADATA
shtym-0.2.0.dist-info/WHEEL
shtym-0.2.0.dist-info/entry_points.txt
shtym-0.2.0.dist-info/top_level.txt
shtym-0.2.0.dist-info/RECORD
