Metadata-Version: 2.4
Name: shtym
Version: 0.2.0
Summary: AI-powered summary filter that distills any command's output.
Author: osoken
License-Expression: MIT
Project-URL: Homepage, https://github.com/osoekawaitlab/shtym-py
Project-URL: Repository, https://github.com/osoekawaitlab/shtym-py
Classifier: Development Status :: 4 - Beta
Classifier: Intended Audience :: Developers
Classifier: Operating System :: POSIX
Classifier: Programming Language :: Python :: 3 :: Only
Classifier: Programming Language :: Python :: 3.10
Classifier: Programming Language :: Python :: 3.11
Classifier: Programming Language :: Python :: 3.12
Classifier: Programming Language :: Python :: 3.13
Classifier: Typing :: Typed
Requires-Python: >=3.10
License-File: LICENSE
Requires-Dist: pydantic>=2.12.4
Requires-Dist: tomli>=2.0.0; python_full_version < "3.11"
Provides-Extra: ollama
Requires-Dist: ollama>=0.6.1; extra == "ollama"
Dynamic: license-file
